lustre/__init__.py
lustre/lustre.yaml
lustre/charts/team/fsx-storageclass/.helmignore
lustre/charts/team/fsx-storageclass/Chart.yaml
lustre/charts/team/fsx-storageclass/values.yaml
lustre/charts/team/fsx-storageclass/templates/_helpers.tpl
lustre/charts/team/fsx-storageclass/templates/podsettings.yaml
lustre/charts/team/fsx-storageclass/templates/pvc.yaml
lustre/charts/team/fsx-storageclass/templates/storageclass.yaml
lustre/charts/user/fsx-filesystem/.helmignore
lustre/charts/user/fsx-filesystem/Chart.yaml
lustre/charts/user/fsx-filesystem/values.yaml
lustre/charts/user/fsx-filesystem/templates/_helpers.tpl
lustre/charts/user/fsx-filesystem/templates/pvc.yaml
aws_orbit_lustre-1.4.0.dist-info/METADATA
aws_orbit_lustre-1.4.0.dist-info/VERSION
aws_orbit_lustre-1.4.0.dist-info/WHEEL
aws_orbit_lustre-1.4.0.dist-info/top_level.txt
aws_orbit_lustre-1.4.0.dist-info/RECORD
